MANIFEST.in
README.md
setup.cfg
setup.py
donecal/__init__.py
donecal/donecal.py
donecal/version.txt
python_donecal.egg-info/PKG-INFO
python_donecal.egg-info/SOURCES.txt
python_donecal.egg-info/dependency_links.txt
python_donecal.egg-info/entry_points.txt
python_donecal.egg-info/not-zip-safe
python_donecal.egg-info/requires.txt
python_donecal.egg-info/top_level.txt