Metadata-Version: 1.0
Name: python-donecal
Version: 0.3.2
Summary: Python interface for the donecal.com restful HTTP API
Home-page: http://donecal.com/help/API#Python
Author: Peter Bengtsson
Author-email: mail@peterbe.com
License: BSD
Keywords: donecal rest api donecal.com
Platform: UNKNOWN
